grebarss_reader/__init__.py
grebarss_reader/cacher.py
grebarss_reader/config.py
grebarss_reader/converter.py
grebarss_reader/getter.py
grebarss_reader/grebarss_parser.py
grebarss_reader/printer.py
grebarss_reader/rss_reader.py
grebarss_reader/urlmarker.py
grebarss_reader/database/db.json
grebarss_reader/fonts/DejaVuSans-Bold.ttf
grebarss_reader/fonts/DejaVuSans-BoldOblique.ttf
grebarss_reader/fonts/DejaVuSans-ExtraLight.ttf
grebarss_reader/fonts/DejaVuSans-Oblique.ttf
grebarss_reader/fonts/DejaVuSans.ttf
grebarss_reader/templates/html_template.jinja2
tests/__init__.py
tests/test_cacher.py
tests/test_converter.py
tests/test_geter.py
tests/test_grebarss_parser.py
tests/test_printer.py
grebarss-4.1.12.dist-info/LICENSE.txt
grebarss-4.1.12.dist-info/METADATA
grebarss-4.1.12.dist-info/WHEEL
grebarss-4.1.12.dist-info/entry_points.txt
grebarss-4.1.12.dist-info/top_level.txt
grebarss-4.1.12.dist-info/RECORD
